params.v
`define SCREEN_W    64
`define SCREEN_H    64
`define TILE_SIZE   8
`define COORD_BITS  16
`define DEPTH_BITS  16
`define TILE_BITS  3
`define TILE_SHIFT 3
`define COLOR_BITS  8

edge_function.v
`include "params.v" 
module edge_function #(
    parameter COORD_BITS  = `COORD_BITS,   
    parameter RESULT_BITS = 33             
)(
    input  wire signed [COORD_BITS-1:0] x0, y0,  
    input  wire signed [COORD_BITS-1:0] x1, y1,  
    input  wire signed [COORD_BITS-1:0] px, py,  

    output wire signed [RESULT_BITS-1:0] result, 
    output wire inside_flag
);

wire signed [COORD_BITS:0] dx = px - x0;   
wire signed [COORD_BITS:0] dy = py - y0;   
wire signed [COORD_BITS:0] ex = x1 - x0;   
wire signed [COORD_BITS:0] ey = y1 - y0;

assign result = (dx * ey) - (dy * ex);
wire is_horizontal = (y1 == y0);
assign inside_flag = is_horizontal ? (result < 0) : (result <= 0);

endmodule

edge_function_tb.v
`timescale 1ns/1ps
`include "params.v"

module edge_function_tb;

    reg signed [`COORD_BITS-1:0] px, py;   
    localparam signed [`COORD_BITS-1:0] V0X = 16'sd2,  V0Y = 16'sd2;
    localparam signed [`COORD_BITS-1:0] V1X = 16'sd8,  V1Y = 16'sd2;
    localparam signed [`COORD_BITS-1:0] V2X = 16'sd5,  V2Y = 16'sd7;

    wire signed [32:0] result_e0, result_e1, result_e2;
    wire inside_flag_e0, inside_flag_e1, inside_flag_e2;
    wire inside_triangle = inside_flag_e0 & inside_flag_e1 & inside_flag_e2;

    edge_function #(
        .COORD_BITS(`COORD_BITS),
        .RESULT_BITS(33)
    ) edge0 (
        .x0(V0X), .y0(V0Y),
        .x1(V1X), .y1(V1Y),
        .px(px),  .py(py),
        .result(result_e0),
        .inside_flag(inside_flag_e0)
    );

    edge_function #(
        .COORD_BITS(`COORD_BITS),
        .RESULT_BITS(33)
    ) edge1 (
        .x0(V1X), .y0(V1Y),
        .x1(V2X), .y1(V2Y),
        .px(px),  .py(py),
        .result(result_e1),
        .inside_flag(inside_flag_e1)
    );

    edge_function #(
        .COORD_BITS(`COORD_BITS),
        .RESULT_BITS(33)
    ) edge2 (
        .x0(V2X), .y0(V2Y),
        .x1(V0X), .y1(V0Y),
        .px(px),  .py(py),
        .result(result_e2),
        .inside_flag(inside_flag_e2)
    );

    integer pass_count, fail_count;

    task check;
        input signed [`COORD_BITS-1:0] test_px, test_py;
        input expected_inside;
        input [127:0] label;  
        begin
            px = test_px;
            py = test_py;
            #1; 

            if (inside_triangle === expected_inside) begin
                $display("PASS | %s | px=%0d py=%0d | inside=%b (expected %b) | e0=%0d e1=%0d e2=%0d",
                    label, test_px, test_py, inside_triangle, expected_inside,
                    result_e0, result_e1, result_e2);
                pass_count = pass_count + 1;
            end else begin
                $display("FAIL | %s | px=%0d py=%0d | inside=%b (expected %b) | e0=%0d e1=%0d e2=%0d",
                    label, test_px, test_py, inside_triangle, expected_inside,
                    result_e0, result_e1, result_e2);
                fail_count = fail_count + 1;
            end
        end
    endtask

    initial begin
        pass_count = 0;
        fail_count = 0;

        $display("=================================================");
        $display("  edge_function_tb — Triangle (2,2),(8,2),(5,7)  ");
        $display("=================================================");

        check(16'sd5, 16'sd4, 1'b1, "INSIDE center   ");
        check(16'sd5, 16'sd1, 1'b0, "OUTSIDE above   ");
        check(16'sd0, 16'sd4, 1'b0, "OUTSIDE left    ");
        check(16'sd5, 16'sd2, 1'b0, "ON top edge     ");
        check(16'sd3, 16'sd4, 1'b0, "NEAR left edge  ");
        check(16'sd2, 16'sd2, 1'b0, "AT vertex V0    ");
        check(16'sd8, 16'sd2, 1'b0, "AT vertex V1    ");
        check(16'sd5, 16'sd7, 1'b1, "AT vertex V2    ");
        check(16'sd5, 16'sd6, 1'b1, "INSIDE near tip ");
        check(-16'sd5, -16'sd5, 1'b0, "OUTSIDE neg     ");

        $display("=================================================");
        $display("  RESULTS: %0d PASSED,  %0d FAILED", pass_count, fail_count);
        $display("=================================================");

        if (fail_count == 0)
            $display("ALL TESTS PASSED");
            
        $finish;
    end

    initial begin
        $dumpfile("edge_function_tb.vcd");
        $dumpvars(0, edge_function_tb);
    end

endmodule

edge_function_tb.vcd
$date
	Thu May 28 17:33:34 2026
$end
$version
	Icarus Verilog
$end
$timescale
	1ps
$end
$scope module edge_function_tb $end
$var wire 1 ! inside_triangle $end
$var wire 33 " result_e2 [32:0] $end
$var wire 33 # result_e1 [32:0] $end
$var wire 33 $ result_e0 [32:0] $end
$var wire 1 % inside_flag_e2 $end
$var wire 1 & inside_flag_e1 $end
$var wire 1 ' inside_flag_e0 $end
$var parameter 16 ( V0X $end
$var parameter 16 ) V0Y $end
$var parameter 16 * V1X $end
$var parameter 16 + V1Y $end
$var parameter 16 , V2X $end
$var parameter 16 - V2Y $end
$var reg 16 . px [15:0] $end
$var reg 16 / py [15:0] $end
$var integer 32 0 fail_count [31:0] $end
$var integer 32 1 pass_count [31:0] $end
$scope module edge0 $end
$var wire 16 2 px [15:0] $end
$var wire 16 3 py [15:0] $end
$var wire 16 4 x0 [15:0] $end
$var wire 16 5 x1 [15:0] $end
$var wire 16 6 y0 [15:0] $end
$var wire 16 7 y1 [15:0] $end
$var wire 33 8 result [32:0] $end
$var wire 1 9 is_horizontal $end
$var wire 1 ' inside_flag $end
$var wire 17 : ey [16:0] $end
$var wire 17 ; ex [16:0] $end
$var wire 17 < dy [16:0] $end
$var wire 17 = dx [16:0] $end
$var parameter 32 > COORD_BITS $end
$var parameter 32 ? RESULT_BITS $end
$upscope $end
$scope module edge1 $end
$var wire 16 @ px [15:0] $end
$var wire 16 A py [15:0] $end
$var wire 16 B x0 [15:0] $end
$var wire 16 C x1 [15:0] $end
$var wire 16 D y0 [15:0] $end
$var wire 16 E y1 [15:0] $end
$var wire 33 F result [32:0] $end
$var wire 1 G is_horizontal $end
$var wire 1 & inside_flag $end
$var wire 17 H ey [16:0] $end
$var wire 17 I ex [16:0] $end
$var wire 17 J dy [16:0] $end
$var wire 17 K dx [16:0] $end
$var parameter 32 L COORD_BITS $end
$var parameter 32 M RESULT_BITS $end
$upscope $end
$scope module edge2 $end
$var wire 16 N px [15:0] $end
$var wire 16 O py [15:0] $end
$var wire 16 P x0 [15:0] $end
$var wire 16 Q x1 [15:0] $end
$var wire 16 R y0 [15:0] $end
$var wire 16 S y1 [15:0] $end
$var wire 33 T result [32:0] $end
$var wire 1 U is_horizontal $end
$var wire 1 % inside_flag $end
$var wire 17 V ey [16:0] $end
$var wire 17 W ex [16:0] $end
$var wire 17 X dy [16:0] $end
$var wire 17 Y dx [16:0] $end
$var parameter 32 Z COORD_BITS $end
$var parameter 32 [ RESULT_BITS $end
$upscope $end
$scope task check $end
$var reg 1 \ expected_inside $end
$var reg 128 ] label [127:0] $end
$var reg 16 ^ test_px [15:0] $end
$var reg 16 _ test_py [15:0] $end
$upscope $end
$upscope $end
$enddefinitions $end
$comment Show the parameter values. $end
$dumpall
b100001 [
b10000 Z
b100001 M
b10000 L
b100001 ?
b10000 >
b111 -
b101 ,
b10 +
b1000 *
b10 )
b10 (
$end
#0
$dumpvars
b100 _
b101 ^
b1001001010011100101001101001001010001000100010100100000011000110110010101101110011101000110010101110010001000000010000000100000 ]
1\
b0 Y
b11111111111111101 X
b11111111111111101 W
b11111111111111011 V
0U
b111111111111111111111111111110111 T
b10 S
b111 R
b10 Q
b101 P
b100 O
b101 N
b11111111111111101 K
b10 J
b11111111111111101 I
b101 H
0G
b111111111111111111111111111110111 F
b111 E
b10 D
b101 C
b1000 B
b100 A
b101 @
b11 =
b10 <
b110 ;
b0 :
19
b111111111111111111111111111110100 8
b10 7
b10 6
b1000 5
b10 4
b100 3
b101 2
b0 1
b0 0
b100 /
b101 .
1'
1&
1%
b111111111111111111111111111110100 $
b111111111111111111111111111110111 #
b111111111111111111111111111110111 "
1!
$end
#1000
0!
0'
b110 $
b110 8
b11111111111111111 <
b111111111111111111111111111101110 #
b111111111111111111111111111101110 F
b11111111111111111 J
b111111111111111111111111111101110 "
b111111111111111111111111111101110 T
b11111111111111010 X
b1 /
b1 3
b1 A
b1 O
b1001111010101010101010001010011010010010100010001000101001000000110000101100010011011110111011001100101001000000010000000100000 ]
0\
b1 _
b1 1
#2000
1'
0%
b111111111111111111111111111110100 $
b111111111111111111111111111110100 8
b10 <
b10 J
b11111111111111101 X
b100 /
b100 3
b100 A
b100 O
b11111111111111110 =
b111111111111111111111111111011110 #
b111111111111111111111111111011110 F
b11111111111111000 K
b10000 "
b10000 T
b11111111111111011 Y
b0 .
b0 2
b0 @
b0 N
b1001111010101010101010001010011010010010100010001000101001000000110110001100101011001100111010000100000001000000010000000100000 ]
b100 _
b0 ^
b10 1
#3000
0!
0'
1%
b0 $
b0 8
b0 <
b0 J
b11111111111111011 X
b10 /
b10 3
b10 A
b10 O
b11 =
b111111111111111111111111111110001 #
b111111111111111111111111111110001 F
b11111111111111101 K
b111111111111111111111111111110001 "
b111111111111111111111111111110001 T
b0 Y
b101 .
b101 2
b101 @
b101 N
b1001111010011100010000001110100011011110111000000100000011001010110010001100111011001010010000000100000001000000010000000100000 ]
b10 _
b101 ^
b11 1
#4000
1'
0%
b111111111111111111111111111110100 $
b111111111111111111111111111110100 8
b10 <
b10 J
b11111111111111101 X
b100 /
b100 3
b100 A
b100 O
b1 =
b111111111111111111111111111101101 #
b111111111111111111111111111101101 F
b11111111111111011 K
b1 "
b1 T
b11111111111111110 Y
b11 .
b11 2
b11 @
b11 N
b1001110010001010100000101010010001000000110110001100101011001100111010000100000011001010110010001100111011001010010000000100000 ]
b100 _
b11 ^
b100 1
#5000
0!
0'
1%
b0 $
b0 8
b0 <
b0 J
b11111111111111011 X
b10 /
b10 3
b10 A
b10 O
b0 =
b111111111111111111111111111100010 #
b111111111111111111111111111100010 F
b11111111111111010 K
b0 "
b0 T
b11111111111111101 Y
b10 .
b10 2
b10 @
b10 N
b1000001010101000010000001110110011001010111001001110100011001010111100000100000010101100011000000100000001000000010000000100000 ]
b10 _
b10 ^
b101 1
#6000
b110 =
b0 #
b0 F
b0 K
b111111111111111111111111111100010 "
b111111111111111111111111111100010 T
b11 Y
b1000 .
b1000 2
b1000 @
b1000 N
b1000001010101000010000001110110011001010111001001110100011001010111100000100000010101100011000100100000001000000010000000100000 ]
b1000 ^
b110 1
#7000
1!
1'
b111111111111111111111111111100010 $
b111111111111111111111111111100010 8
b101 <
b101 J
b0 X
b111 /
b111 3
b111 A
b111 O
b11 =
b0 #
b0 F
b11111111111111101 K
b0 "
b0 T
b0 Y
b101 .
b101 2
b101 @
b101 N
b1000001010101000010000001110110011001010111001001110100011001010111100000100000010101100011001000100000001000000010000000100000 ]
1\
b111 _
b101 ^
b111 1
#8000
b111111111111111111111111111101000 $
b111111111111111111111111111101000 8
b100 <
b111111111111111111111111111111101 #
b111111111111111111111111111111101 F
b100 J
b111111111111111111111111111111101 "
b111111111111111111111111111111101 T
b11111111111111111 X
b110 /
b110 3
b110 A
b110 O
b1001001010011100101001101001001010001000100010100100000011011100110010101100001011100100010000001110100011010010111000000100000 ]
b110 _
b1000 1
#9000
0!
0'
0%
b101010 $
b101010 8
b11111111111111001 <
b11111111111111001 J
b11111111111110100 X
b1111111111111011 /
b1111111111111011 3
b1111111111111011 A
b1111111111111011 O
b11111111111111001 =
b111111111111111111111111110101010 #
b111111111111111111111111110101010 F
b11111111111110011 K
b1110 "
b1110 T
b11111111111110110 Y
b1111111111111011 .
b1111111111111011 2
b1111111111111011 @
b1111111111111011 N
b1001111010101010101010001010011010010010100010001000101001000000110111001100101011001110010000000100000001000000010000000100000 ]
0\
b1111111111111011 _
b1111111111111011 ^
b1001 1
#10000
b1010 1
