framebuffer.v
module framebuffer (
    input  wire clk,
    input  wire rst,
    input  wire write_en,
    input  wire [5:0] write_x,
    input  wire [5:0] write_y,
    input  wire [7:0] write_color,
    input  wire read_en,
    input  wire [5:0] read_x,
    input  wire [5:0] read_y,
    output reg  [7:0] read_color,
    input  wire dump_en
);

    reg [7:0] fb [0:63][0:63];
    integer i, j;

    always @(posedge clk) begin
        if (rst) begin
            for (i = 0; i < 64; i = i + 1)
                for (j = 0; j < 64; j = j + 1)
                    fb[i][j] <= 8'h00;
        end else begin
            if (write_en)
                fb[write_y][write_x] <= write_color;

            if (read_en)
                read_color <= fb[read_y][read_x];

            if (dump_en) begin
                begin : dump_block
                    integer fd;
                    fd = $fopen("framebuffer_dump.hex", "w");
                    for (i = 0; i < 64; i = i + 1)
                        for (j = 0; j < 64; j = j + 1)
                            $fwrite(fd, "%02h\n", fb[i][j]);
                    $fclose(fd);
                end
            end
        end
    end

endmodule

output_merger.v
module output_merger (
    input  wire clk,
    input  wire rst,
    input  wire pixel_valid_in,
    input  wire [5:0]  pixel_x,
    input  wire [5:0]  pixel_y,
    input  wire [7:0]  pixel_color_in,
    input  wire [15:0] pixel_depth_in,

    output reg  zbuf_read_en,
    output reg  [5:0]  zbuf_read_x,
    output reg  [5:0]  zbuf_read_y,
    input  wire [15:0] zbuf_depth_out,
    output reg  zbuf_write_en,
    output reg  [5:0]  zbuf_write_x,
    output reg  [5:0]  zbuf_write_y,
    output reg  [15:0] zbuf_depth_in,

    output reg  fb_write_en,
    output reg  [5:0]  fb_write_x,
    output reg  [5:0]  fb_write_y,
    output reg  [7:0]  fb_write_color
);

    reg s1_valid;
    reg [5:0]  s1_x, s1_y;
    reg [7:0]  s1_color;
    reg [15:0] s1_depth;

    always @(posedge clk) begin
        if (rst) begin
            zbuf_read_en  <= 0;
            zbuf_write_en <= 0;
            fb_write_en   <= 0;
            s1_valid      <= 0;
        end else begin
            zbuf_write_en <= 0;
            fb_write_en   <= 0;
            zbuf_read_en <= pixel_valid_in;
            zbuf_read_x  <= pixel_x;
            zbuf_read_y  <= pixel_y;
            s1_valid     <= pixel_valid_in;
            s1_x         <= pixel_x;
            s1_y         <= pixel_y;
            s1_color     <= pixel_color_in;
            s1_depth     <= pixel_depth_in;

            if (s1_valid) begin
                if (s1_depth < zbuf_depth_out) begin
                    zbuf_write_en <= 1;
                    zbuf_write_x  <= s1_x;
                    zbuf_write_y  <= s1_y;
                    zbuf_depth_in <= s1_depth;
                    fb_write_en    <= 1;
                    fb_write_x     <= s1_x;
                    fb_write_y     <= s1_y;
                    fb_write_color <= s1_color;
                end
            end
        end
    end

endmodule

zbuffer.v
module zbuffer (
    input  wire clk,
    input  wire rst,
    input  wire read_en,
    input  wire write_en,
    input  wire [5:0]  read_x,
    input  wire [5:0]  read_y,
    input  wire [5:0]  write_x,
    input  wire [5:0]  write_y,
    input  wire [15:0] depth_in,
    output reg  [15:0] depth_out
);

    reg [15:0] zbuf [0:63][0:63];
    integer i, j;

    always @(posedge clk) begin
        if (rst) begin
            for (i = 0; i < 64; i = i + 1)
                for (j = 0; j < 64; j = j + 1)
                    zbuf[i][j] <= 16'hFFFF;
        end else begin
            if (write_en)
                zbuf[write_y][write_x] <= depth_in;

            if (read_en)
                depth_out <= zbuf[read_y][read_x];
        end
    end

endmodule

params.v
`define SCREEN_W    64
`define SCREEN_H    64
`define TILE_SIZE   8
`define COORD_BITS  16
`define DEPTH_BITS  16
`define TILE_BITS  3
`define TILE_SHIFT 3
`define COLOR_BITS  8

edge_function.v
`include "params.v" 
module edge_function #(
    parameter COORD_BITS  = `COORD_BITS,   
    parameter RESULT_BITS = 33             
)(
    input  wire signed [COORD_BITS-1:0] x0, y0,  
    input  wire signed [COORD_BITS-1:0] x1, y1,  
    input  wire signed [COORD_BITS-1:0] px, py,  

    output wire signed [RESULT_BITS-1:0] result, 
    output wire inside_flag
);

wire signed [COORD_BITS:0] dx = px - x0;   
wire signed [COORD_BITS:0] dy = py - y0;   
wire signed [COORD_BITS:0] ex = x1 - x0;   
wire signed [COORD_BITS:0] ey = y1 - y0;

assign result = (dx * ey) - (dy * ex);
wire is_horizontal = (y1 == y0);
assign inside_flag = is_horizontal ? (result < 0) : (result <= 0);

endmodule

tile_rasterizer.v
`include "params.v"

module tile_rasterizer (
    input  wire clk,
    input  wire rst,
    input  wire start,

    input  wire [`COORD_BITS-1:0]  tile_ox,
    input  wire [`COORD_BITS-1:0]  tile_oy,

    input  wire [`COORD_BITS-1:0]  v0x, v0y,
    input  wire [`COORD_BITS-1:0]  v1x, v1y,
    input  wire [`COORD_BITS-1:0]  v2x, v2y,

    input  wire [`COLOR_BITS-1:0]  color_in,

    output wire pixel_valid,
    output wire [`COORD_BITS-1:0]  pixel_x,
    output wire [`COORD_BITS-1:0]  pixel_y,
    output wire [`COLOR_BITS-1:0]  pixel_color,
    output wire done
);

    localparam IDLE   = 2'd0;
    localparam LOAD   = 2'd1;
    localparam RASTER = 2'd2;
    localparam DONE_S = 2'd3;

    reg [1:0] state;

    reg [2:0] px, py;
    reg [`COORD_BITS-1:0] tile_ox_r, tile_oy_r;
    reg [`COORD_BITS-1:0] v0x_r, v0y_r;
    reg [`COORD_BITS-1:0] v1x_r, v1y_r;
    reg [`COORD_BITS-1:0] v2x_r, v2y_r;
    reg [`COLOR_BITS-1:0] color_r;

    wire [`COORD_BITS-1:0] abs_x = tile_ox_r + {{(`COORD_BITS-3){1'b0}}, px};
    wire [`COORD_BITS-1:0] abs_y = tile_oy_r + {{(`COORD_BITS-3){1'b0}}, py};

    wire inside0, inside1, inside2;

    edge_function ef0 (
        .x0(v0x_r), .y0(v0y_r),
        .x1(v1x_r), .y1(v1y_r),
        .px(abs_x),  .py(abs_y),
        .inside_flag(inside0)
    );

    edge_function ef1 (
        .x0(v1x_r), .y0(v1y_r),
        .x1(v2x_r), .y1(v2y_r),
        .px(abs_x),  .py(abs_y),
        .inside_flag(inside1)
    );

    edge_function ef2 (
        .x0(v2x_r), .y0(v2y_r),
        .x1(v0x_r), .y1(v0y_r),
        .px(abs_x),  .py(abs_y),
        .inside_flag(inside2)
    );

    always @(posedge clk) begin
        if (rst) begin
            state <= IDLE;
            px    <= 3'd0;
            py    <= 3'd0;
        end else begin
            case (state)

                IDLE: begin
                    if (start)
                        state <= LOAD;
                end

                LOAD: begin
                    tile_ox_r <= tile_ox;
                    tile_oy_r <= tile_oy;
                    v0x_r <= v0x; v0y_r <= v0y;
                    v1x_r <= v1x; v1y_r <= v1y;
                    v2x_r <= v2x; v2y_r <= v2y;
                    color_r   <= color_in;
                    px <= 3'd0;
                    py <= 3'd0;
                    state <= RASTER;
                end

                RASTER: begin
                    if (px == 3'd7) begin
                        px <= 3'd0;
                        if (py == 3'd7)
                            state <= DONE_S;
                        else
                            py <= py + 3'd1;
                    end else begin
                        px <= px + 3'd1;
                    end
                end

                DONE_S: begin
                    state <= IDLE;
                end

            endcase
        end
    end

    assign pixel_valid  = (state == RASTER) && inside0 && inside1 && inside2;
    assign pixel_x      = abs_x;
    assign pixel_y      = abs_y;
    assign pixel_color  = color_r;
    assign done         = (state == DONE_S);

endmodule

tile_binner.v
`include "params.v"
module tile_binner #(
    parameter COORD_BITS = `COORD_BITS,
    parameter SCREEN_W   = `SCREEN_W,
    parameter SCREEN_H   = `SCREEN_H,
    parameter TILE_SIZE  = `TILE_SIZE,
    parameter TILE_SHIFT = 3,   
    parameter TILE_BITS  = 3          
)(
    input wire signed [COORD_BITS-1:0] V0x, V0y,
    input wire signed [COORD_BITS-1:0] V1x, V1y,
    input wire signed [COORD_BITS-1:0] V2x, V2y,

    output wire [TILE_BITS-1:0] tile_x_min, tile_x_max,
    output wire [TILE_BITS-1:0] tile_y_min, tile_y_max,
    output wire valid_out,
    output wire no_overlap
);

wire signed [COORD_BITS-1:0] min_x, min_y, max_x, max_y;

assign min_x = (V0x < V1x) ? ((V0x < V2x) ? V0x : V2x) : ((V1x < V2x) ? V1x : V2x);
assign min_y = (V0y < V1y) ? ((V0y < V2y) ? V0y : V2y) : ((V1y < V2y) ? V1y : V2y);
assign max_x = (V0x > V1x) ? ((V0x > V2x) ? V0x : V2x) : ((V1x > V2x) ? V1x : V2x);
assign max_y = (V0y > V1y) ? ((V0y > V2y) ? V0y : V2y) : ((V1y > V2y) ? V1y : V2y);

wire signed [COORD_BITS-1:0] clamped_x_min = (min_x < 0) ? 0 : ((min_x > SCREEN_W-1) ? SCREEN_W-1 : min_x);
wire signed [COORD_BITS-1:0] clamped_y_min = (min_y < 0) ? 0 : ((min_y > SCREEN_H-1) ? SCREEN_H-1 : min_y);
wire signed [COORD_BITS-1:0] clamped_x_max = (max_x < 0) ? 0 : ((max_x > SCREEN_W-1) ? SCREEN_W-1 : max_x);
wire signed [COORD_BITS-1:0] clamped_y_max = (max_y < 0) ? 0 : ((max_y > SCREEN_H-1) ? SCREEN_H-1 : max_y);

wire off_screen = (min_x >= SCREEN_W) || (min_y >= SCREEN_H) || (max_x < 0) || (max_y < 0);

assign tile_x_min = clamped_x_min[COORD_BITS-1:TILE_SHIFT];
assign tile_x_max = clamped_x_max[COORD_BITS-1:TILE_SHIFT];
assign tile_y_min = clamped_y_min[COORD_BITS-1:TILE_SHIFT];
assign tile_y_max = clamped_y_max[COORD_BITS-1:TILE_SHIFT];

assign valid_out = !off_screen;
assign no_overlap =  off_screen;

endmodule

gpu_top.v
module gpu_top (
    input  wire clk,
    input  wire rst,
    input  wire [15:0] v0x,
    input  wire [15:0] v0y,
    input  wire [15:0] v1x,
    input  wire [15:0] v1y,
    input  wire [15:0] v2x,
    input  wire [15:0] v2y,
    input  wire [7:0]  tri_color,
    input  wire [15:0] tri_depth,
    input  wire raster_start,
    input  wire dump_en
);

    wire [2:0] tile_x_min;
    wire [2:0] tile_x_max;
    wire [2:0] tile_y_min;
    wire [2:0] tile_y_max;
    wire tile_valid;
    wire no_overlap;

    tile_binner binner (
        .V0x(v0x),
        .V0y(v0y),
        .V1x(v1x),
        .V1y(v1y),
        .V2x(v2x),
        .V2y(v2y),
        .tile_x_min(tile_x_min),
        .tile_x_max(tile_x_max),
        .tile_y_min(tile_y_min),
        .tile_y_max(tile_y_max),
        .valid_out(tile_valid),
        .no_overlap(no_overlap)
    );

    wire pixel_valid;
    wire [15:0] pixel_x;
    wire [15:0] pixel_y;
    wire [7:0] pixel_color;
    wire raster_done;

    tile_rasterizer rasterizer (
        .clk(clk),
        .rst(rst),
        .start(raster_start),
        .tile_ox({10'd0, tile_x_min, 3'b000}),
        .tile_oy({10'd0, tile_y_min, 3'b000}),
        .v0x(v0x),
        .v0y(v0y),
        .v1x(v1x),
        .v1y(v1y),
        .v2x(v2x),
        .v2y(v2y),
        .color_in(tri_color),
        .pixel_valid(pixel_valid),
        .pixel_x(pixel_x),
        .pixel_y(pixel_y),
        .pixel_color(pixel_color),
        .done(raster_done)
    );

    wire zbuf_read_en;
    wire [5:0] zbuf_read_x;
    wire [5:0] zbuf_read_y;
    wire zbuf_write_en;
    wire [5:0] zbuf_write_x;
    wire [5:0] zbuf_write_y;
    wire [15:0] zbuf_depth_in;
    wire [15:0] zbuf_depth_out;

    zbuffer zbuf (
        .clk(clk),
        .rst(rst),
        .read_en(zbuf_read_en),
        .write_en(zbuf_write_en),
        .read_x(zbuf_read_x),
        .read_y(zbuf_read_y),
        .write_x(zbuf_write_x),
        .write_y(zbuf_write_y),
        .depth_in(zbuf_depth_in),
        .depth_out(zbuf_depth_out)
    );

    wire fb_write_en;
    wire [5:0] fb_write_x;
    wire [5:0] fb_write_y;
    wire [7:0] fb_write_color;

    output_merger merger (
        .clk(clk),
        .rst(rst),
        .pixel_valid_in(pixel_valid),
        .pixel_x(pixel_x[5:0]),
        .pixel_y(pixel_y[5:0]),
        .pixel_color_in(pixel_color),
        .pixel_depth_in(tri_depth),
        .zbuf_read_en(zbuf_read_en),
        .zbuf_read_x(zbuf_read_x),
        .zbuf_read_y(zbuf_read_y),
        .zbuf_depth_out(zbuf_depth_out),
        .zbuf_write_en(zbuf_write_en),
        .zbuf_write_x(zbuf_write_x),
        .zbuf_write_y(zbuf_write_y),
        .zbuf_depth_in(zbuf_depth_in),
        .fb_write_en(fb_write_en),
        .fb_write_x(fb_write_x),
        .fb_write_y(fb_write_y),
        .fb_write_color(fb_write_color)
    );

    framebuffer fb (
        .clk(clk),
        .rst(rst),
        .write_en(fb_write_en),
        .write_x(fb_write_x),
        .write_y(fb_write_y),
        .write_color(fb_write_color),
        .read_en(1'b0),
        .read_x(6'd0),
        .read_y(6'd0),
        .read_color(),
        .dump_en(dump_en)
    );

endmodule

tb_gpu_top.v
`timescale 1ns/1ps

module gpu_top_tb;
    reg clk;
    reg rst;
    reg [15:0] v0x;
    reg [15:0] v0y;
    reg [15:0] v1x;
    reg [15:0] v1y;
    reg [15:0] v2x;
    reg [15:0] v2y;
    reg [7:0] tri_color;
    reg [15:0] tri_depth;
    reg raster_start;
    reg dump_en;

    gpu_top dut (
        .clk(clk),
        .rst(rst),
        .v0x(v0x),
        .v0y(v0y),
        .v1x(v1x),
        .v1y(v1y),
        .v2x(v2x),
        .v2y(v2y),
        .tri_color(tri_color),
        .tri_depth(tri_depth),
        .raster_start(raster_start),
        .dump_en(dump_en)
    );

    initial begin
        clk = 0;
        forever #5 clk = ~clk;
    end

    initial begin

        rst = 1;
        raster_start = 0;
        dump_en = 0;
        #20;
        rst = 0;

        v0x = 16'd10;
        v0y = 16'd10;
        v1x = 16'd30;
        v1y = 16'd10;
        v2x = 16'd20;
        v2y = 16'd30;
        tri_color = 8'hFF;
        tri_depth = 16'd100;

        #20;
        raster_start = 1;
        #10;
        raster_start = 0;
        #5000;
        dump_en = 1;
        #10;
        dump_en = 0;
        #100; 
        $finish;

    end

    initial begin
        $dumpfile("gpu_top.vcd");
        $dumpvars(0, gpu_top_tb);
    end

endmodule

gpu_top.vcd
$date
	Tue Jun 02 18:58:31 2026
$end
$version
	Icarus Verilog
$end
$timescale
	1ps
$end
$scope module gpu_top_tb $end
$var reg 1 ! clk $end
$var reg 1 " dump_en $end
$var reg 1 # raster_start $end
$var reg 1 $ rst $end
$var reg 8 % tri_color [7:0] $end
$var reg 16 & tri_depth [15:0] $end
$var reg 16 ' v0x [15:0] $end
$var reg 16 ( v0y [15:0] $end
$var reg 16 ) v1x [15:0] $end
$var reg 16 * v1y [15:0] $end
$var reg 16 + v2x [15:0] $end
$var reg 16 , v2y [15:0] $end
$scope module dut $end
$var wire 1 ! clk $end
$var wire 1 " dump_en $end
$var wire 1 # raster_start $end
$var wire 1 $ rst $end
$var wire 8 - tri_color [7:0] $end
$var wire 16 . tri_depth [15:0] $end
$var wire 16 / v0x [15:0] $end
$var wire 16 0 v0y [15:0] $end
$var wire 16 1 v1x [15:0] $end
$var wire 16 2 v1y [15:0] $end
$var wire 16 3 v2x [15:0] $end
$var wire 16 4 v2y [15:0] $end
$var wire 6 5 zbuf_write_y [5:0] $end
$var wire 6 6 zbuf_write_x [5:0] $end
$var wire 1 7 zbuf_write_en $end
$var wire 6 8 zbuf_read_y [5:0] $end
$var wire 6 9 zbuf_read_x [5:0] $end
$var wire 1 : zbuf_read_en $end
$var wire 16 ; zbuf_depth_out [15:0] $end
$var wire 16 < zbuf_depth_in [15:0] $end
$var wire 3 = tile_y_min [2:0] $end
$var wire 3 > tile_y_max [2:0] $end
$var wire 3 ? tile_x_min [2:0] $end
$var wire 3 @ tile_x_max [2:0] $end
$var wire 1 A tile_valid $end
$var wire 1 B raster_done $end
$var wire 16 C pixel_y [15:0] $end
$var wire 16 D pixel_x [15:0] $end
$var wire 1 E pixel_valid $end
$var wire 8 F pixel_color [7:0] $end
$var wire 1 G no_overlap $end
$var wire 6 H fb_write_y [5:0] $end
$var wire 6 I fb_write_x [5:0] $end
$var wire 1 J fb_write_en $end
$var wire 8 K fb_write_color [7:0] $end
$scope module binner $end
$var wire 16 L V0x [15:0] $end
$var wire 16 M V0y [15:0] $end
$var wire 16 N V1x [15:0] $end
$var wire 16 O V1y [15:0] $end
$var wire 16 P V2x [15:0] $end
$var wire 16 Q V2y [15:0] $end
$var wire 1 G no_overlap $end
$var wire 1 R off_screen $end
$var wire 1 A valid_out $end
$var wire 3 S tile_y_min [2:0] $end
$var wire 3 T tile_y_max [2:0] $end
$var wire 3 U tile_x_min [2:0] $end
$var wire 3 V tile_x_max [2:0] $end
$var wire 16 W min_y [15:0] $end
$var wire 16 X min_x [15:0] $end
$var wire 16 Y max_y [15:0] $end
$var wire 16 Z max_x [15:0] $end
$var wire 16 [ clamped_y_min [15:0] $end
$var wire 16 \ clamped_y_max [15:0] $end
$var wire 16 ] clamped_x_min [15:0] $end
$var wire 16 ^ clamped_x_max [15:0] $end
$var parameter 32 _ COORD_BITS $end
$var parameter 32 ` SCREEN_H $end
$var parameter 32 a SCREEN_W $end
$var parameter 32 b TILE_BITS $end
$var parameter 32 c TILE_SHIFT $end
$var parameter 32 d TILE_SIZE $end
$upscope $end
$scope module fb $end
$var wire 1 ! clk $end
$var wire 1 " dump_en $end
$var wire 1 e read_en $end
$var wire 6 f read_x [5:0] $end
$var wire 6 g read_y [5:0] $end
$var wire 1 $ rst $end
$var wire 6 h write_y [5:0] $end
$var wire 6 i write_x [5:0] $end
$var wire 1 J write_en $end
$var wire 8 j write_color [7:0] $end
$var reg 8 k read_color [7:0] $end
$var integer 32 l i [31:0] $end
$var integer 32 m j [31:0] $end
$scope begin dump_block $end
$var integer 32 n fd [31:0] $end
$upscope $end
$upscope $end
$scope module merger $end
$var wire 1 ! clk $end
$var wire 16 o pixel_depth_in [15:0] $end
$var wire 6 p pixel_x [5:0] $end
$var wire 6 q pixel_y [5:0] $end
$var wire 1 $ rst $end
$var wire 16 r zbuf_depth_out [15:0] $end
$var wire 1 E pixel_valid_in $end
$var wire 8 s pixel_color_in [7:0] $end
$var reg 8 t fb_write_color [7:0] $end
$var reg 1 J fb_write_en $end
$var reg 6 u fb_write_x [5:0] $end
$var reg 6 v fb_write_y [5:0] $end
$var reg 8 w s1_color [7:0] $end
$var reg 16 x s1_depth [15:0] $end
$var reg 1 y s1_valid $end
$var reg 6 z s1_x [5:0] $end
$var reg 6 { s1_y [5:0] $end
$var reg 16 | zbuf_depth_in [15:0] $end
$var reg 1 : zbuf_read_en $end
$var reg 6 } zbuf_read_x [5:0] $end
$var reg 6 ~ zbuf_read_y [5:0] $end
$var reg 1 7 zbuf_write_en $end
$var reg 6 !" zbuf_write_x [5:0] $end
$var reg 6 "" zbuf_write_y [5:0] $end
$upscope $end
$scope module rasterizer $end
$var wire 1 ! clk $end
$var wire 8 #" color_in [7:0] $end
$var wire 8 $" pixel_color [7:0] $end
$var wire 1 E pixel_valid $end
$var wire 16 %" pixel_x [15:0] $end
$var wire 16 &" pixel_y [15:0] $end
$var wire 1 $ rst $end
$var wire 1 # start $end
$var wire 16 '" tile_ox [15:0] $end
$var wire 16 (" tile_oy [15:0] $end
$var wire 16 )" v0x [15:0] $end
$var wire 16 *" v0y [15:0] $end
$var wire 16 +" v1x [15:0] $end
$var wire 16 ," v1y [15:0] $end
$var wire 16 -" v2x [15:0] $end
$var wire 16 ." v2y [15:0] $end
$var wire 1 /" inside2 $end
$var wire 1 0" inside1 $end
$var wire 1 1" inside0 $end
$var wire 1 B done $end
$var wire 16 2" abs_y [15:0] $end
$var wire 16 3" abs_x [15:0] $end
$var parameter 2 4" DONE_S $end
$var parameter 2 5" IDLE $end
$var parameter 2 6" LOAD $end
$var parameter 2 7" RASTER $end
$var reg 8 8" color_r [7:0] $end
$var reg 3 9" px [2:0] $end
$var reg 3 :" py [2:0] $end
$var reg 2 ;" state [1:0] $end
$var reg 16 <" tile_ox_r [15:0] $end
$var reg 16 =" tile_oy_r [15:0] $end
$var reg 16 >" v0x_r [15:0] $end
$var reg 16 ?" v0y_r [15:0] $end
$var reg 16 @" v1x_r [15:0] $end
$var reg 16 A" v1y_r [15:0] $end
$var reg 16 B" v2x_r [15:0] $end
$var reg 16 C" v2y_r [15:0] $end
$scope module ef0 $end
$var wire 16 D" px [15:0] $end
$var wire 16 E" py [15:0] $end
$var wire 16 F" x0 [15:0] $end
$var wire 16 G" x1 [15:0] $end
$var wire 16 H" y0 [15:0] $end
$var wire 16 I" y1 [15:0] $end
$var wire 33 J" result [32:0] $end
$var wire 1 K" is_horizontal $end
$var wire 1 1" inside_flag $end
$var wire 17 L" ey [16:0] $end
$var wire 17 M" ex [16:0] $end
$var wire 17 N" dy [16:0] $end
$var wire 17 O" dx [16:0] $end
$var parameter 32 P" COORD_BITS $end
$var parameter 32 Q" RESULT_BITS $end
$upscope $end
$scope module ef1 $end
$var wire 16 R" px [15:0] $end
$var wire 16 S" py [15:0] $end
$var wire 16 T" x0 [15:0] $end
$var wire 16 U" x1 [15:0] $end
$var wire 16 V" y0 [15:0] $end
$var wire 16 W" y1 [15:0] $end
$var wire 33 X" result [32:0] $end
$var wire 1 Y" is_horizontal $end
$var wire 1 0" inside_flag $end
$var wire 17 Z" ey [16:0] $end
$var wire 17 [" ex [16:0] $end
$var wire 17 \" dy [16:0] $end
$var wire 17 ]" dx [16:0] $end
$var parameter 32 ^" COORD_BITS $end
$var parameter 32 _" RESULT_BITS $end
$upscope $end
$scope module ef2 $end
$var wire 16 `" px [15:0] $end
$var wire 16 a" py [15:0] $end
$var wire 16 b" x0 [15:0] $end
$var wire 16 c" x1 [15:0] $end
$var wire 16 d" y0 [15:0] $end
$var wire 16 e" y1 [15:0] $end
$var wire 33 f" result [32:0] $end
$var wire 1 g" is_horizontal $end
$var wire 1 /" inside_flag $end
$var wire 17 h" ey [16:0] $end
$var wire 17 i" ex [16:0] $end
$var wire 17 j" dy [16:0] $end
$var wire 17 k" dx [16:0] $end
$var parameter 32 l" COORD_BITS $end
$var parameter 32 m" RESULT_BITS $end
$upscope $end
$upscope $end
$scope module zbuf $end
$var wire 1 ! clk $end
$var wire 16 n" depth_in [15:0] $end
$var wire 1 : read_en $end
$var wire 6 o" read_x [5:0] $end
$var wire 6 p" read_y [5:0] $end
$var wire 1 $ rst $end
$var wire 1 7 write_en $end
$var wire 6 q" write_x [5:0] $end
$var wire 6 r" write_y [5:0] $end
$var reg 16 s" depth_out [15:0] $end
$var integer 32 t" i [31:0] $end
$var integer 32 u" j [31:0] $end
$upscope $end
$upscope $end
$upscope $end
$enddefinitions $end
$comment Show the parameter values. $end
$dumpall
b100001 m"
b10000 l"
b100001 _"
b10000 ^"
b100001 Q"
b10000 P"
b10 7"
b1 6"
b0 5"
b11 4"
b1000 d
b11 c
b11 b
b1000000 a
b1000000 `
b10000 _
$end
#0
$dumpvars
bx u"
bx t"
bx s"
bx r"
bx q"
bx p"
bx o"
bx n"
bx k"
bx j"
bx i"
bx h"
xg"
bx f"
bx e"
bx d"
bx c"
bx b"
bx a"
bx `"
bx ]"
bx \"
bx ["
bx Z"
xY"
bx X"
bx W"
bx V"
bx U"
bx T"
bx S"
bx R"
bx O"
bx N"
bx M"
bx L"
xK"
bx J"
bx I"
bx H"
bx G"
bx F"
bx E"
bx D"
bx C"
bx B"
bx A"
bx @"
bx ?"
bx >"
bx ="
bx <"
bx ;"
bx :"
bx 9"
bx 8"
bx 3"
bx 2"
x1"
x0"
x/"
bx ."
bx -"
bx ,"
bx +"
bx *"
bx )"
b0xxx000 ("
b0xxx000 '"
bx &"
bx %"
bx $"
bx #"
bx ""
bx !"
bx ~
bx }
bx |
bx {
bx z
xy
bx x
bx w
bx v
bx u
bx t
bx s
bx r
bx q
bx p
bx o
bx n
bx m
bx l
bx k
bx j
bx i
bx h
b0 g
b0 f
0e
bx ^
bx ]
bx \
bx [
bx Z
bx Y
bx X
bx W
bx V
bx U
bx T
bx S
xR
bx Q
bx P
bx O
bx N
bx M
bx L
bx K
xJ
bx I
bx H
xG
bx F
xE
bx D
bx C
xB
xA
bx @
bx ?
bx >
bx =
bx <
bx ;
x:
bx 9
bx 8
x7
bx 6
bx 5
bx 4
bx 3
bx 2
bx 1
bx 0
bx /
bx .
bx -
bx ,
bx +
bx *
bx )
bx (
bx '
bx &
bx %
1$
0#
0"
0!
$end
#5000
0E
b0 :"
b0 9"
0B
b0 ;"
0y
0J
07
0:
b1000000 u"
b1000000 t"
b1000000 m
b1000000 l
1!
#10000
0!
#15000
b1000000 m
b1000000 l
b1000000 u"
b1000000 t"
1!
#20000
b1000 ("
b1 =
b1 S
b11 >
b11 T
b1000 '"
b1 ?
b1 U
b11 @
b11 V
0G
1A
0R
b1010 [
b11110 \
b1010 ]
b11110 ^
b1010 W
b11110 Y
b1010 X
b11110 Z
0!
b1100100 &
b1100100 .
b1100100 o
b11111111 %
b11111111 -
b11111111 #"
b11110 ,
b11110 4
b11110 Q
b11110 ."
b10100 +
b10100 3
b10100 P
b10100 -"
b1010 *
b1010 2
b1010 O
b1010 ,"
b11110 )
b11110 1
b11110 N
b11110 +"
b1010 (
b1010 0
b1010 M
b1010 *"
b1010 '
b1010 /
b1010 L
b1010 )"
0$
#25000
b1100100 x
1!
#30000
0!
#35000
1!
#40000
0!
1#
#45000
b1 ;"
1!
#50000
0!
0#
#55000
10"
0/"
01"
b1000 q
b1000 p
b10 ;"
b11111111 F
b11111111 s
b11111111 $"
b11111111 8"
b111111111111111111111111000110100 X"
b10100 Z"
0Y"
b10100 f"
b11111111111101010 j"
b11111111111101100 h"
0g"
b11110 C"
b11110 W"
b11110 d"
b11111111111110110 ["
b11111111111110100 k"
b11111111111110110 i"
b10100 B"
b10100 U"
b10100 b"
b101000 J"
b0 L"
1K"
b11111111111111110 \"
b1010 A"
b1010 I"
b1010 V"
b10100 M"
b11111111111101010 ]"
b11110 @"
b11110 G"
b11110 T"
b11111111111111110 N"
b1010 ?"
b1010 H"
b1010 e"
b11111111111111110 O"
b1010 >"
b1010 F"
b1010 c"
b1000 C
b1000 &"
b1000 2"
b1000 E"
b1000 S"
b1000 a"
b1000 ="
b1000 D
b1000 %"
b1000 3"
b1000 D"
b1000 R"
b1000 `"
b1000 <"
1!
#60000
0!
#65000
1/"
b1001 p
b11111111111111111 O"
b111111111111111111111111001001000 X"
b11111111111101011 ]"
b0 f"
b11111111111110101 k"
b1001 D
b1001 %"
b1001 3"
b1001 D"
b1001 R"
b1001 `"
b1 9"
b11111111 w
b1000 {
b1000 z
b1000 8
b1000 ~
b1000 p"
b1000 9
b1000 }
b1000 o"
1!
#70000
0!
#75000
b1010 p
b1001 z
b1001 9
b1001 }
b1001 o"
b0 O"
b111111111111111111111111001011100 X"
b11111111111101100 ]"
b111111111111111111111111111101100 f"
b11111111111110110 k"
b1010 D
b1010 %"
b1010 3"
b1010 D"
b1010 R"
b1010 `"
b10 9"
1!
#80000
0!
#85000
b1011 p
b1 O"
b111111111111111111111111001110000 X"
b11111111111101101 ]"
b111111111111111111111111111011000 f"
b11111111111110111 k"
b1011 D
b1011 %"
b1011 3"
b1011 D"
b1011 R"
b1011 `"
b11 9"
b1010 z
b1010 9
b1010 }
b1010 o"
1!
#90000
0!
#95000
b1100 p
b1011 z
b1011 9
b1011 }
b1011 o"
b10 O"
b111111111111111111111111010000100 X"
b11111111111101110 ]"
b111111111111111111111111111000100 f"
b11111111111111000 k"
b1100 D
b1100 %"
b1100 3"
b1100 D"
b1100 R"
b1100 `"
b100 9"
1!
#100000
0!
#105000
b1101 p
b11 O"
b111111111111111111111111010011000 X"
b11111111111101111 ]"
b111111111111111111111111110110000 f"
b11111111111111001 k"
b1101 D
b1101 %"
b1101 3"
b1101 D"
b1101 R"
b1101 `"
b101 9"
b1100 z
b1100 9
b1100 }
b1100 o"
1!
#110000
0!
#115000
b1110 p
b1101 z
b1101 9
b1101 }
b1101 o"
b100 O"
b111111111111111111111111010101100 X"
b11111111111110000 ]"
b111111111111111111111111110011100 f"
b11111111111111010 k"
b1110 D
b1110 %"
b1110 3"
b1110 D"
b1110 R"
b1110 `"
b110 9"
1!
#120000
0!
#125000
b1111 p
b101 O"
b111111111111111111111111011000000 X"
b11111111111110001 ]"
b111111111111111111111111110001000 f"
b11111111111111011 k"
b1111 D
b1111 %"
b1111 3"
b1111 D"
b1111 R"
b1111 `"
b111 9"
b1110 z
b1110 9
b1110 }
b1110 o"
1!
#130000
0!
#135000
b1001 q
0/"
b1000 p
b1111 z
b1111 9
b1111 }
b1111 o"
b10100 J"
b11111111111111111 N"
b11111111111111111 \"
b11111111111101011 j"
b1001 C
b1001 &"
b1001 2"
b1001 E"
b1001 S"
b1001 a"
b1 :"
b11111111111111110 O"
b111111111111111111111111000111110 X"
b11111111111101010 ]"
b11110 f"
b11111111111110100 k"
b1000 D
b1000 %"
b1000 3"
b1000 D"
b1000 R"
b1000 `"
b0 9"
1!
#140000
0!
#145000
b1001 p
b11111111111111111 O"
b111111111111111111111111001010010 X"
b11111111111101011 ]"
b1010 f"
b11111111111110101 k"
b1001 D
b1001 %"
b1001 3"
b1001 D"
b1001 R"
b1001 `"
b1 9"
b1001 {
b1000 z
b1001 8
b1001 ~
b1001 p"
b1000 9
b1000 }
b1000 o"
1!
#150000
0!
#155000
1/"
b1010 p
b1001 z
b1001 9
b1001 }
b1001 o"
b0 O"
b111111111111111111111111001100110 X"
b11111111111101100 ]"
b111111111111111111111111111110110 f"
b11111111111110110 k"
b1010 D
b1010 %"
b1010 3"
b1010 D"
b1010 R"
b1010 `"
b10 9"
1!
#160000
0!
#165000
b1011 p
b1 O"
b111111111111111111111111001111010 X"
b11111111111101101 ]"
b111111111111111111111111111100010 f"
b11111111111110111 k"
b1011 D
b1011 %"
b1011 3"
b1011 D"
b1011 R"
b1011 `"
b11 9"
b1010 z
b1010 9
b1010 }
b1010 o"
1!
#170000
0!
