params.v
`define SCREEN_W    64
`define SCREEN_H    64
`define TILE_SIZE   8
`define COORD_BITS  16
`define DEPTH_BITS  16
`define TILE_BITS  3
`define TILE_SHIFT 3
`define COLOR_BITS  8

tile_binner.v
`include "params.v"
module tile_binner #(
    parameter COORD_BITS = `COORD_BITS,
    parameter SCREEN_W   = `SCREEN_W,
    parameter SCREEN_H   = `SCREEN_H,
    parameter TILE_SIZE  = `TILE_SIZE,
    parameter TILE_SHIFT = 3,   
    parameter TILE_BITS  = 3          
)(
    input wire signed [COORD_BITS-1:0] V0x, V0y,
    input wire signed [COORD_BITS-1:0] V1x, V1y,
    input wire signed [COORD_BITS-1:0] V2x, V2y,

    output wire [TILE_BITS-1:0] tile_x_min, tile_x_max,
    output wire [TILE_BITS-1:0] tile_y_min, tile_y_max,
    output wire valid_out,
    output wire no_overlap
);

wire signed [COORD_BITS-1:0] min_x, min_y, max_x, max_y;

assign min_x = (V0x < V1x) ? ((V0x < V2x) ? V0x : V2x) : ((V1x < V2x) ? V1x : V2x);
assign min_y = (V0y < V1y) ? ((V0y < V2y) ? V0y : V2y) : ((V1y < V2y) ? V1y : V2y);
assign max_x = (V0x > V1x) ? ((V0x > V2x) ? V0x : V2x) : ((V1x > V2x) ? V1x : V2x);
assign max_y = (V0y > V1y) ? ((V0y > V2y) ? V0y : V2y) : ((V1y > V2y) ? V1y : V2y);

wire signed [COORD_BITS-1:0] clamped_x_min = (min_x < 0) ? 0 : ((min_x > SCREEN_W-1) ? SCREEN_W-1 : min_x);
wire signed [COORD_BITS-1:0] clamped_y_min = (min_y < 0) ? 0 : ((min_y > SCREEN_H-1) ? SCREEN_H-1 : min_y);
wire signed [COORD_BITS-1:0] clamped_x_max = (max_x < 0) ? 0 : ((max_x > SCREEN_W-1) ? SCREEN_W-1 : max_x);
wire signed [COORD_BITS-1:0] clamped_y_max = (max_y < 0) ? 0 : ((max_y > SCREEN_H-1) ? SCREEN_H-1 : max_y);

wire off_screen = (min_x >= SCREEN_W) || (min_y >= SCREEN_H) || (max_x < 0) || (max_y < 0);

assign tile_x_min = clamped_x_min[COORD_BITS-1:TILE_SHIFT];
assign tile_x_max = clamped_x_max[COORD_BITS-1:TILE_SHIFT];
assign tile_y_min = clamped_y_min[COORD_BITS-1:TILE_SHIFT];
assign tile_y_max = clamped_y_max[COORD_BITS-1:TILE_SHIFT];

assign valid_out = !off_screen;
assign no_overlap =  off_screen;

endmodule

tb_tile_binner.v
`timescale 1ns/1ps

module tb_tile_binner;

    localparam COORD_BITS = 16;
    localparam SCREEN_W   = 64;
    localparam SCREEN_H   = 64;
    localparam TILE_SIZE  = 8;
    localparam TILE_BITS  = 3;

    reg  clk;
    reg  rst;
    reg  valid_in;

    reg  [COORD_BITS-1:0] v0x, v0y;
    reg  [COORD_BITS-1:0] v1x, v1y;
    reg  [COORD_BITS-1:0] v2x, v2y;

    wire [TILE_BITS-1:0]  tile_x_min;
    wire [TILE_BITS-1:0]  tile_x_max;
    wire [TILE_BITS-1:0]  tile_y_min;
    wire [TILE_BITS-1:0]  tile_y_max;

    wire valid_out;
    wire no_overlap;

    tile_binner #(
        .COORD_BITS(COORD_BITS),
        .SCREEN_W  (SCREEN_W),
        .SCREEN_H  (SCREEN_H),
        .TILE_SIZE (TILE_SIZE)
    ) dut (
        .V0x       (v0x),
        .V0y       (v0y),
        .V1x       (v1x),
        .V1y       (v1y),
        .V2x       (v2x),
        .V2y       (v2y),
        .tile_x_min(tile_x_min),
        .tile_x_max(tile_x_max),
        .tile_y_min(tile_y_min),
        .tile_y_max(tile_y_max),
        .valid_out (valid_out),
        .no_overlap(no_overlap)
    );

    initial clk = 0;
    always #5 clk = ~clk;

    initial begin
        $dumpfile("tb_tile_binner.vcd");
        $dumpvars(0, tb_tile_binner);
    end

    integer pass_count;
    integer fail_count;
    integer test_id;

    task submit_and_check;
        input [COORD_BITS-1:0] i_v0x, i_v0y;
        input [COORD_BITS-1:0] i_v1x, i_v1y;
        input [COORD_BITS-1:0] i_v2x, i_v2y;
        input [TILE_BITS-1:0]  exp_tx_min, exp_tx_max;
        input [TILE_BITS-1:0]  exp_ty_min, exp_ty_max;
        input                  exp_no_overlap;
        begin
            v0x = i_v0x; v0y = i_v0y;
            v1x = i_v1x; v1y = i_v1y;
            v2x = i_v2x; v2y = i_v2y;

            @(posedge clk); #1;
            valid_in = 1'b1;
            @(posedge clk); #1;
            valid_in = 1'b0;

            @(posedge clk); #1;

            if (no_overlap !== exp_no_overlap) begin
                $display("FAIL [test %0d]: no_overlap = %b, expected %b",
                         test_id, no_overlap, exp_no_overlap);
                fail_count = fail_count + 1;
            end else if (exp_no_overlap) begin
                $display("PASS [test %0d]: triangle off-screen, no_overlap asserted", test_id);
                pass_count = pass_count + 1;
            end else if (tile_x_min !== exp_tx_min || tile_x_max !== exp_tx_max ||
                         tile_y_min !== exp_ty_min || tile_y_max !== exp_ty_max) begin
                $display("FAIL [test %0d]: got tx=[%0d:%0d] ty=[%0d:%0d], expected tx=[%0d:%0d] ty=[%0d:%0d]",
                         test_id,
                         tile_x_min, tile_x_max, tile_y_min, tile_y_max,
                         exp_tx_min, exp_tx_max, exp_ty_min, exp_ty_max);
                fail_count = fail_count + 1;
            end else begin
                $display("PASS [test %0d]: tx=[%0d:%0d] ty=[%0d:%0d]",
                         test_id, tile_x_min, tile_x_max, tile_y_min, tile_y_max);
                pass_count = pass_count + 1;
            end

            test_id = test_id + 1;
            @(posedge clk);
        end
    endtask

    initial begin
        pass_count = 0;
        fail_count = 0;
        test_id    = 1;

        rst      = 1'b1;
        valid_in = 1'b0;
        v0x = 0; v0y = 0;
        v1x = 0; v1y = 0;
        v2x = 0; v2y = 0;
        repeat(3) @(posedge clk);
        rst = 1'b0;
        @(posedge clk);

        submit_and_check(
            16'd0,  16'd0,
            16'd28, 16'd0,
            16'd0,  16'd28,
            3'd0, 3'd3,
            3'd0, 3'd3,
            1'b0
        );

        submit_and_check(
            16'd0,  16'd0,
            16'd63, 16'd0,
            16'd0,  16'd63,
            3'd0, 3'd7,
            3'd0, 3'd7,
            1'b0
        );

        submit_and_check(
            16'd80,  16'd80,
            16'd100, 16'd80,
            16'd80,  16'd100,
            3'd0, 3'd0,
            3'd0, 3'd0,
            1'b1
        );

        submit_and_check(
            16'd2, 16'd2,
            16'd5, 16'd2,
            16'd2, 16'd5,
            3'd0, 3'd0,
            3'd0, 3'd0,
            1'b0
        );

        $display("-------------------------------");
        $display("Results: %0d PASS, %0d FAIL", pass_count, fail_count);
        if (fail_count == 0)
            $display("ALL TESTS PASSED");
        else
            $display("SOME TESTS FAILED — check output above");
        $display("-------------------------------");

        $finish;
    end

    initial begin
        #10000;
        $display("TIMEOUT — simulation hung");
        $finish;
    end

endmodule

tb_tile_binner.vcd
$date
	Sat May 30 16:47:29 2026
$end
$version
	Icarus Verilog
$end
$timescale
	1ps
$end
$scope module tb_tile_binner $end
$var wire 1 ! valid_out $end
$var wire 3 " tile_y_min [2:0] $end
$var wire 3 # tile_y_max [2:0] $end
$var wire 3 $ tile_x_min [2:0] $end
$var wire 3 % tile_x_max [2:0] $end
$var wire 1 & no_overlap $end
$var parameter 32 ' COORD_BITS $end
$var parameter 32 ( SCREEN_H $end
$var parameter 32 ) SCREEN_W $end
$var parameter 32 * TILE_BITS $end
$var parameter 32 + TILE_SIZE $end
$var reg 1 , clk $end
$var reg 1 - rst $end
$var reg 16 . v0x [15:0] $end
$var reg 16 / v0y [15:0] $end
$var reg 16 0 v1x [15:0] $end
$var reg 16 1 v1y [15:0] $end
$var reg 16 2 v2x [15:0] $end
$var reg 16 3 v2y [15:0] $end
$var reg 1 4 valid_in $end
$var integer 32 5 fail_count [31:0] $end
$var integer 32 6 pass_count [31:0] $end
$var integer 32 7 test_id [31:0] $end
$scope module dut $end
$var wire 16 8 V0x [15:0] $end
$var wire 16 9 V0y [15:0] $end
$var wire 16 : V1x [15:0] $end
$var wire 16 ; V1y [15:0] $end
$var wire 16 < V2x [15:0] $end
$var wire 16 = V2y [15:0] $end
$var wire 1 & no_overlap $end
$var wire 1 > off_screen $end
$var wire 1 ! valid_out $end
$var wire 3 ? tile_y_min [2:0] $end
$var wire 3 @ tile_y_max [2:0] $end
$var wire 3 A tile_x_min [2:0] $end
$var wire 3 B tile_x_max [2:0] $end
$var wire 16 C min_y [15:0] $end
$var wire 16 D min_x [15:0] $end
$var wire 16 E max_y [15:0] $end
$var wire 16 F max_x [15:0] $end
$var wire 16 G clamped_y_min [15:0] $end
$var wire 16 H clamped_y_max [15:0] $end
$var wire 16 I clamped_x_min [15:0] $end
$var wire 16 J clamped_x_max [15:0] $end
$var parameter 32 K COORD_BITS $end
$var parameter 32 L SCREEN_H $end
$var parameter 32 M SCREEN_W $end
$var parameter 32 N TILE_BITS $end
$var parameter 32 O TILE_SHIFT $end
$var parameter 32 P TILE_SIZE $end
$upscope $end
$scope task submit_and_check $end
$var reg 1 Q exp_no_overlap $end
$var reg 3 R exp_tx_max [2:0] $end
$var reg 3 S exp_tx_min [2:0] $end
$var reg 3 T exp_ty_max [2:0] $end
$var reg 3 U exp_ty_min [2:0] $end
$var reg 16 V i_v0x [15:0] $end
$var reg 16 W i_v0y [15:0] $end
$var reg 16 X i_v1x [15:0] $end
$var reg 16 Y i_v1y [15:0] $end
$var reg 16 Z i_v2x [15:0] $end
$var reg 16 [ i_v2y [15:0] $end
$upscope $end
$upscope $end
$enddefinitions $end
$comment Show the parameter values. $end
$dumpall
b1000 P
b11 O
b11 N
b1000000 M
b1000000 L
b10000 K
b1000 +
b11 *
b1000000 )
b1000000 (
b10000 '
$end
#0
$dumpvars
bx [
bx Z
bx Y
bx X
bx W
bx V
bx U
bx T
bx S
bx R
xQ
b0 J
b0 I
b0 H
b0 G
b0 F
b0 E
b0 D
b0 C
b0 B
b0 A
b0 @
b0 ?
0>
b0 =
b0 <
b0 ;
b0 :
b0 9
b0 8
b1 7
b0 6
b0 5
04
b0 3
b0 2
b0 1
b0 0
b0 /
b0 .
1-
0,
0&
b0 %
b0 $
b0 #
b0 "
1!
$end
#5000
1,
#10000
0,
#15000
1,
#20000
0,
#25000
0-
1,
#30000
0,
#35000
b11 #
b11 @
b11 %
b11 B
b11100 H
b11100 J
b11100 E
b11100 F
b11100 3
b11100 =
b11100 0
b11100 :
0Q
b11 T
b0 U
b11 R
b0 S
b11100 [
b0 Z
b0 Y
b11100 X
b0 W
b0 V
1,
#40000
0,
#45000
1,
#46000
14
#50000
0,
#55000
1,
#56000
04
#60000
0,
#65000
1,
#66000
b10 7
b1 6
#70000
0,
#75000
b111 #
b111 @
b111 %
b111 B
b111111 H
b111111 J
b111111 E
b111111 F
b111111 3
b111111 =
b111111 0
b111111 :
b111 T
b111 R
b111111 [
b111111 X
1,
#80000
0,
#85000
1,
#86000
14
#90000
0,
#95000
1,
#96000
04
#100000
0,
#105000
1,
#106000
b11 7
b10 6
#110000
0,
#115000
b111 $
b111 A
b111 "
b111 ?
b111111 I
b111111 G
1&
0!
1>
b1010000 D
b1010000 C
b1100100 E
b1100100 F
b1100100 3
b1100100 =
b1010000 2
b1010000 <
b1010000 1
b1010000 ;
b1100100 0
b1100100 :
b1010000 /
b1010000 9
b1010000 .
b1010000 8
1Q
b0 T
b0 R
b1100100 [
b1010000 Z
b1010000 Y
b1100100 X
b1010000 W
b1010000 V
1,
#120000
0,
#125000
1,
#126000
14
#130000
0,
#135000
1,
#136000
04
#140000
0,
#145000
1,
#146000
b100 7
b11 6
#150000
0,
#155000
b0 #
b0 @
b0 "
b0 ?
b0 %
b0 B
b0 $
b0 A
b101 H
b10 G
b101 J
b10 I
0&
1!
0>
b101 E
b10 C
b101 F
b10 D
b101 3
b101 =
b10 2
b10 <
b10 1
b10 ;
b101 0
b101 :
b10 /
b10 9
b10 .
b10 8
0Q
b101 [
b10 Z
b10 Y
b101 X
b10 W
b10 V
1,
#160000
0,
#165000
1,
#166000
14
#170000
0,
#175000
1,
#176000
04
#180000
0,
#185000
1,
#186000
b101 7
b100 6
