params.v
`define SCREEN_W    64
`define SCREEN_H    64
`define TILE_SIZE   8
`define COORD_BITS  16
`define DEPTH_BITS  16
`define TILE_BITS  3
`define TILE_SHIFT 3
`define COLOR_BITS  8

edge_function.v
`include "params.v" 
module edge_function #(
    parameter COORD_BITS  = `COORD_BITS,   
    parameter RESULT_BITS = 33             
)(
    input  wire signed [COORD_BITS-1:0] x0, y0,  
    input  wire signed [COORD_BITS-1:0] x1, y1,  
    input  wire signed [COORD_BITS-1:0] px, py,  

    output wire signed [RESULT_BITS-1:0] result, 
    output wire inside_flag
);

wire signed [COORD_BITS:0] dx = px - x0;   
wire signed [COORD_BITS:0] dy = py - y0;   
wire signed [COORD_BITS:0] ex = x1 - x0;   
wire signed [COORD_BITS:0] ey = y1 - y0;

assign result = (dx * ey) - (dy * ex);
wire is_horizontal = (y1 == y0);
assign inside_flag = is_horizontal ? (result < 0) : (result <= 0);

endmodule

tile_rasterizer.v
`include "params.v"

module tile_rasterizer (
    input  wire clk,
    input  wire rst,
    input  wire start,

    input  wire [`COORD_BITS-1:0]  tile_ox,
    input  wire [`COORD_BITS-1:0]  tile_oy,

    input  wire [`COORD_BITS-1:0]  v0x, v0y,
    input  wire [`COORD_BITS-1:0]  v1x, v1y,
    input  wire [`COORD_BITS-1:0]  v2x, v2y,

    input  wire [`COLOR_BITS-1:0]  color_in,

    output wire pixel_valid,
    output wire [`COORD_BITS-1:0]  pixel_x,
    output wire [`COORD_BITS-1:0]  pixel_y,
    output wire [`COLOR_BITS-1:0]  pixel_color,
    output wire done
);

    localparam IDLE   = 2'd0;
    localparam LOAD   = 2'd1;
    localparam RASTER = 2'd2;
    localparam DONE_S = 2'd3;

    reg [1:0] state;

    reg [2:0] px, py;
    reg [`COORD_BITS-1:0] tile_ox_r, tile_oy_r;
    reg [`COORD_BITS-1:0] v0x_r, v0y_r;
    reg [`COORD_BITS-1:0] v1x_r, v1y_r;
    reg [`COORD_BITS-1:0] v2x_r, v2y_r;
    reg [`COLOR_BITS-1:0] color_r;

    wire [`COORD_BITS-1:0] abs_x = tile_ox_r + {{(`COORD_BITS-3){1'b0}}, px};
    wire [`COORD_BITS-1:0] abs_y = tile_oy_r + {{(`COORD_BITS-3){1'b0}}, py};

    wire inside0, inside1, inside2;

    edge_function ef0 (
        .x0(v0x_r), .y0(v0y_r),
        .x1(v1x_r), .y1(v1y_r),
        .px(abs_x),  .py(abs_y),
        .inside_flag(inside0)
    );

    edge_function ef1 (
        .x0(v1x_r), .y0(v1y_r),
        .x1(v2x_r), .y1(v2y_r),
        .px(abs_x),  .py(abs_y),
        .inside_flag(inside1)
    );

    edge_function ef2 (
        .x0(v2x_r), .y0(v2y_r),
        .x1(v0x_r), .y1(v0y_r),
        .px(abs_x),  .py(abs_y),
        .inside_flag(inside2)
    );

    always @(posedge clk) begin
        if (rst) begin
            state <= IDLE;
            px    <= 3'd0;
            py    <= 3'd0;
        end else begin
            case (state)

                IDLE: begin
                    if (start)
                        state <= LOAD;
                end

                LOAD: begin
                    tile_ox_r <= tile_ox;
                    tile_oy_r <= tile_oy;
                    v0x_r <= v0x; v0y_r <= v0y;
                    v1x_r <= v1x; v1y_r <= v1y;
                    v2x_r <= v2x; v2y_r <= v2y;
                    color_r   <= color_in;
                    px <= 3'd0;
                    py <= 3'd0;
                    state <= RASTER;
                end

                RASTER: begin
                    if (px == 3'd7) begin
                        px <= 3'd0;
                        if (py == 3'd7)
                            state <= DONE_S;
                        else
                            py <= py + 3'd1;
                    end else begin
                        px <= px + 3'd1;
                    end
                end

                DONE_S: begin
                    state <= IDLE;
                end

            endcase
        end
    end

    assign pixel_valid  = (state == RASTER) && inside0 && inside1 && inside2;
    assign pixel_x      = abs_x;
    assign pixel_y      = abs_y;
    assign pixel_color  = color_r;
    assign done         = (state == DONE_S);

endmodule

tb_tile_rasterizer.v
`include "params.v"
`timescale 1ns/1ps

module tb_tile_rasterizer;

    reg  clk, rst, start;
    reg  [`COORD_BITS-1:0] tile_ox, tile_oy;
    reg  [`COORD_BITS-1:0] v0x, v0y, v1x, v1y, v2x, v2y;
    reg  [`COLOR_BITS-1:0] color_in;

    wire pixel_valid;
    wire [`COORD_BITS-1:0]  pixel_x, pixel_y;
    wire [`COLOR_BITS-1:0]  pixel_color;
    wire done;

    tile_rasterizer dut (
        .clk(clk), .rst(rst), .start(start),
        .tile_ox(tile_ox), .tile_oy(tile_oy),
        .v0x(v0x), .v0y(v0y),
        .v1x(v1x), .v1y(v1y),
        .v2x(v2x), .v2y(v2y),
        .color_in(color_in),
        .pixel_valid(pixel_valid),
        .pixel_x(pixel_x), .pixel_y(pixel_y),
        .pixel_color(pixel_color),
        .done(done)
    );

    initial clk = 0;
    always #5 clk = ~clk;
    reg seen [0:7][0:7];   
    integer i, j;

    always @(posedge clk) begin
        if (pixel_valid) begin
            $display("pixel_valid: (%0d, %0d) color=%0h", pixel_x, pixel_y, pixel_color);
            seen[pixel_y][pixel_x] <= 1'b1;
        end
    end
    
    reg expected [0:7][0:7];
    integer fail_count;

    initial begin
        rst = 1; start = 0;
        tile_ox = 0; tile_oy = 0;
        v0x = 0; v0y = 0;
        v1x = 7; v1y = 0;
        v2x = 0; v2y = 7;
        color_in = 8'hAB;

        for (i = 0; i < 8; i = i + 1)
            for (j = 0; j < 8; j = j + 1) begin
                seen[i][j]     = 0;
                expected[i][j] = 0;
            end

        expected[1][0]=1; expected[1][1]=1; expected[1][2]=1; expected[1][3]=1; expected[1][4]=1; expected[1][5]=1; expected[1][6]=1;
        expected[2][0]=1; expected[2][1]=1; expected[2][2]=1; expected[2][3]=1; expected[2][4]=1; expected[2][5]=1;
        expected[3][0]=1; expected[3][1]=1; expected[3][2]=1; expected[3][3]=1; expected[3][4]=1;
        expected[4][0]=1; expected[4][1]=1; expected[4][2]=1; expected[4][3]=1;
        expected[5][0]=1; expected[5][1]=1; expected[5][2]=1;
        expected[6][0]=1; expected[6][1]=1;
        expected[7][0]=1;

        @(posedge clk); @(posedge clk);
        rst = 0;
        @(posedge clk);
        start = 1;
        @(posedge clk);
        start = 0;
        @(posedge done);
        @(posedge clk);  
        fail_count = 0;
        $display("\n--- RESULT CHECK ---");

        for (i = 0; i < 8; i = i + 1) begin
            for (j = 0; j < 8; j = j + 1) begin
                if (expected[i][j] && !seen[i][j]) begin
                    $display("FAIL: pixel (%0d,%0d) expected INSIDE but not seen", j, i);
                    fail_count = fail_count + 1;
                end
                if (!expected[i][j] && seen[i][j]) begin
                    $display("FAIL: pixel (%0d,%0d) fired but expected OUTSIDE", j, i);
                    fail_count = fail_count + 1;
                end
            end
        end

        if (fail_count == 0)
            $display("PASS: all pixels correct");
        else
            $display("FAIL: %0d pixel mismatches", fail_count);

        $finish;
    end

    initial begin
        $dumpfile("tb_tile_rasterizer.vcd");
        $dumpvars(0, tb_tile_rasterizer);
    end

endmodule

tb_tile_rasterizer.vcd
$date
	Mon Jun 01 17:23:30 2026
$end
$version
	Icarus Verilog
$end
$timescale
	1ps
$end
$scope module tb_tile_rasterizer $end
$var wire 16 ! pixel_y [15:0] $end
$var wire 16 " pixel_x [15:0] $end
$var wire 1 # pixel_valid $end
$var wire 8 $ pixel_color [7:0] $end
$var wire 1 % done $end
$var reg 1 & clk $end
$var reg 8 ' color_in [7:0] $end
$var reg 1 ( rst $end
$var reg 1 ) start $end
$var reg 16 * tile_ox [15:0] $end
$var reg 16 + tile_oy [15:0] $end
$var reg 16 , v0x [15:0] $end
$var reg 16 - v0y [15:0] $end
$var reg 16 . v1x [15:0] $end
$var reg 16 / v1y [15:0] $end
$var reg 16 0 v2x [15:0] $end
$var reg 16 1 v2y [15:0] $end
$var integer 32 2 fail_count [31:0] $end
$var integer 32 3 i [31:0] $end
$var integer 32 4 j [31:0] $end
$scope module dut $end
$var wire 1 & clk $end
$var wire 8 5 color_in [7:0] $end
$var wire 8 6 pixel_color [7:0] $end
$var wire 1 # pixel_valid $end
$var wire 16 7 pixel_x [15:0] $end
$var wire 16 8 pixel_y [15:0] $end
$var wire 1 ( rst $end
$var wire 1 ) start $end
$var wire 16 9 tile_ox [15:0] $end
$var wire 16 : tile_oy [15:0] $end
$var wire 16 ; v0x [15:0] $end
$var wire 16 < v0y [15:0] $end
$var wire 16 = v1x [15:0] $end
$var wire 16 > v1y [15:0] $end
$var wire 16 ? v2x [15:0] $end
$var wire 16 @ v2y [15:0] $end
$var wire 1 A inside2 $end
$var wire 1 B inside1 $end
$var wire 1 C inside0 $end
$var wire 1 % done $end
$var wire 16 D abs_y [15:0] $end
$var wire 16 E abs_x [15:0] $end
$var parameter 2 F DONE_S $end
$var parameter 2 G IDLE $end
$var parameter 2 H LOAD $end
$var parameter 2 I RASTER $end
$var reg 8 J color_r [7:0] $end
$var reg 3 K px [2:0] $end
$var reg 3 L py [2:0] $end
$var reg 2 M state [1:0] $end
$var reg 16 N tile_ox_r [15:0] $end
$var reg 16 O tile_oy_r [15:0] $end
$var reg 16 P v0x_r [15:0] $end
$var reg 16 Q v0y_r [15:0] $end
$var reg 16 R v1x_r [15:0] $end
$var reg 16 S v1y_r [15:0] $end
$var reg 16 T v2x_r [15:0] $end
$var reg 16 U v2y_r [15:0] $end
$scope module ef0 $end
$var wire 16 V px [15:0] $end
$var wire 16 W py [15:0] $end
$var wire 16 X x0 [15:0] $end
$var wire 16 Y x1 [15:0] $end
$var wire 16 Z y0 [15:0] $end
$var wire 16 [ y1 [15:0] $end
$var wire 33 \ result [32:0] $end
$var wire 1 ] is_horizontal $end
$var wire 1 C inside_flag $end
$var wire 17 ^ ey [16:0] $end
$var wire 17 _ ex [16:0] $end
$var wire 17 ` dy [16:0] $end
$var wire 17 a dx [16:0] $end
$var parameter 32 b COORD_BITS $end
$var parameter 32 c RESULT_BITS $end
$upscope $end
$scope module ef1 $end
$var wire 16 d px [15:0] $end
$var wire 16 e py [15:0] $end
$var wire 16 f x0 [15:0] $end
$var wire 16 g x1 [15:0] $end
$var wire 16 h y0 [15:0] $end
$var wire 16 i y1 [15:0] $end
$var wire 33 j result [32:0] $end
$var wire 1 k is_horizontal $end
$var wire 1 B inside_flag $end
$var wire 17 l ey [16:0] $end
$var wire 17 m ex [16:0] $end
$var wire 17 n dy [16:0] $end
$var wire 17 o dx [16:0] $end
$var parameter 32 p COORD_BITS $end
$var parameter 32 q RESULT_BITS $end
$upscope $end
$scope module ef2 $end
$var wire 16 r px [15:0] $end
$var wire 16 s py [15:0] $end
$var wire 16 t x0 [15:0] $end
$var wire 16 u x1 [15:0] $end
$var wire 16 v y0 [15:0] $end
$var wire 16 w y1 [15:0] $end
$var wire 33 x result [32:0] $end
$var wire 1 y is_horizontal $end
$var wire 1 A inside_flag $end
$var wire 17 z ey [16:0] $end
$var wire 17 { ex [16:0] $end
$var wire 17 | dy [16:0] $end
$var wire 17 } dx [16:0] $end
$var parameter 32 ~ COORD_BITS $end
$var parameter 32 !" RESULT_BITS $end
$upscope $end
$upscope $end
$upscope $end
$enddefinitions $end
$comment Show the parameter values. $end
$dumpall
b100001 !"
b10000 ~
b100001 q
b10000 p
b100001 c
b10000 b
b10 I
b1 H
b0 G
b11 F
$end
#0
$dumpvars
bx }
bx |
bx {
bx z
xy
bx x
bx w
bx v
bx u
bx t
bx s
bx r
bx o
bx n
bx m
bx l
xk
bx j
bx i
bx h
bx g
bx f
bx e
bx d
bx a
bx `
bx _
bx ^
x]
bx \
bx [
bx Z
bx Y
bx X
bx W
bx V
bx U
bx T
bx S
bx R
bx Q
bx P
bx O
bx N
bx M
bx L
bx K
bx J
bx E
bx D
xC
xB
xA
b111 @
b0 ?
b0 >
b111 =
b0 <
b0 ;
b0 :
b0 9
bx 8
bx 7
bx 6
b10101011 5
b1000 4
b1000 3
bx 2
b111 1
b0 0
b0 /
b111 .
b0 -
b0 ,
b0 +
b0 *
0)
1(
b10101011 '
0&
x%
bx $
x#
bx "
bx !
$end
#5000
0#
b0 L
b0 K
0%
b0 M
1&
#10000
0&
#15000
0(
1&
#20000
0&
#25000
b1 M
1)
1&
#30000
0&
#35000
1B
1A
0C
b10 M
b10101011 $
b10101011 6
b10101011 J
b111111111111111111111111111001111 j
b111 l
0k
b0 x
b11111111111111001 |
b11111111111111001 z
0y
b111 U
b111 i
b111 v
b11111111111111001 m
b0 }
b0 {
b0 T
b0 g
b0 t
b0 \
b0 ^
1]
b0 n
b0 S
b0 [
b0 h
b111 _
b11111111111111001 o
b111 R
b111 Y
b111 f
b0 `
b0 Q
b0 Z
b0 w
b0 a
b0 P
b0 X
b0 u
b0 !
b0 8
b0 D
b0 W
b0 e
b0 s
b0 O
b0 "
b0 7
b0 E
b0 V
b0 d
b0 r
b0 N
0)
1&
#40000
0&
#45000
b1 a
b111111111111111111111111111010110 j
b11111111111111010 o
b111111111111111111111111111111001 x
b1 }
b1 "
b1 7
b1 E
b1 V
b1 d
b1 r
b1 K
1&
#50000
0&
#55000
b10 a
b111111111111111111111111111011101 j
b11111111111111011 o
b111111111111111111111111111110010 x
b10 }
b10 "
b10 7
b10 E
b10 V
b10 d
b10 r
b10 K
1&
#60000
0&
#65000
b11 a
b111111111111111111111111111100100 j
b11111111111111100 o
b111111111111111111111111111101011 x
b11 }
b11 "
b11 7
b11 E
b11 V
b11 d
b11 r
b11 K
1&
#70000
0&
#75000
b100 a
b111111111111111111111111111101011 j
b11111111111111101 o
b111111111111111111111111111100100 x
b100 }
b100 "
b100 7
b100 E
b100 V
b100 d
b100 r
b100 K
1&
#80000
0&
#85000
b101 a
b111111111111111111111111111110010 j
b11111111111111110 o
b111111111111111111111111111011101 x
b101 }
b101 "
b101 7
b101 E
b101 V
b101 d
b101 r
b101 K
1&
#90000
0&
#95000
b110 a
b111111111111111111111111111111001 j
b11111111111111111 o
b111111111111111111111111111010110 x
b110 }
b110 "
b110 7
b110 E
b110 V
b110 d
b110 r
b110 K
1&
#100000
0&
#105000
b111 a
b0 j
b0 o
b111111111111111111111111111001111 x
b111 }
b111 "
b111 7
b111 E
b111 V
b111 d
b111 r
b111 K
1&
#110000
0&
#115000
1#
1C
b111111111111111111111111111111001 \
b1 `
b1 n
b11111111111111010 |
b1 !
b1 8
b1 D
b1 W
b1 e
b1 s
b1 L
b0 a
b111111111111111111111111111010110 j
b11111111111111001 o
b0 x
b0 }
b0 "
b0 7
b0 E
b0 V
b0 d
b0 r
b0 K
1&
#120000
0&
#125000
b1 a
b111111111111111111111111111011101 j
b11111111111111010 o
b111111111111111111111111111111001 x
b1 }
b1 "
b1 7
b1 E
b1 V
b1 d
b1 r
b1 K
1&
#130000
0&
#135000
b10 a
b111111111111111111111111111100100 j
b11111111111111011 o
b111111111111111111111111111110010 x
b10 }
b10 "
b10 7
b10 E
b10 V
b10 d
b10 r
b10 K
1&
#140000
0&
#145000
b11 a
b111111111111111111111111111101011 j
b11111111111111100 o
b111111111111111111111111111101011 x
b11 }
b11 "
b11 7
b11 E
b11 V
b11 d
b11 r
b11 K
1&
#150000
0&
#155000
b100 a
b111111111111111111111111111110010 j
b11111111111111101 o
b111111111111111111111111111100100 x
b100 }
b100 "
b100 7
b100 E
b100 V
b100 d
b100 r
b100 K
1&
#160000
0&
#165000
b101 a
b111111111111111111111111111111001 j
b11111111111111110 o
b111111111111111111111111111011101 x
b101 }
b101 "
b101 7
b101 E
b101 V
b101 d
b101 r
b101 K
1&
#170000
0&
#175000
b110 a
b0 j
b11111111111111111 o
b111111111111111111111111111010110 x
b110 }
b110 "
b110 7
b110 E
b110 V
b110 d
b110 r
b110 K
1&
#180000
0&
#185000
0#
0B
b111 a
b111 j
b0 o
b111111111111111111111111111001111 x
b111 }
b111 "
b111 7
b111 E
b111 V
b111 d
b111 r
b111 K
1&
#190000
0&
#195000
1#
1B
b111111111111111111111111111110010 \
b10 `
b10 n
b11111111111111011 |
b10 !
b10 8
b10 D
b10 W
b10 e
b10 s
b10 L
b0 a
b111111111111111111111111111011101 j
b11111111111111001 o
b0 x
b0 }
b0 "
b0 7
b0 E
b0 V
b0 d
b0 r
b0 K
1&
#200000
0&
#205000
b1 a
b111111111111111111111111111100100 j
b11111111111111010 o
b111111111111111111111111111111001 x
b1 }
b1 "
b1 7
b1 E
b1 V
b1 d
b1 r
b1 K
1&
#210000
0&
#215000
b10 a
b111111111111111111111111111101011 j
b11111111111111011 o
b111111111111111111111111111110010 x
b10 }
b10 "
b10 7
b10 E
b10 V
b10 d
b10 r
b10 K
1&
#220000
0&
#225000
b11 a
b111111111111111111111111111110010 j
b11111111111111100 o
b111111111111111111111111111101011 x
b11 }
b11 "
b11 7
b11 E
b11 V
b11 d
b11 r
b11 K
1&
#230000
0&
#235000
b100 a
b111111111111111111111111111111001 j
b11111111111111101 o
b111111111111111111111111111100100 x
b100 }
b100 "
b100 7
b100 E
b100 V
b100 d
b100 r
b100 K
1&
#240000
0&
#245000
b101 a
b0 j
b11111111111111110 o
b111111111111111111111111111011101 x
b101 }
b101 "
b101 7
b101 E
b101 V
b101 d
b101 r
b101 K
1&
#250000
0&
#255000
0#
0B
b110 a
b111 j
b11111111111111111 o
b111111111111111111111111111010110 x
b110 }
b110 "
b110 7
b110 E
b110 V
b110 d
b110 r
b110 K
1&
#260000
0&
#265000
b111 a
b1110 j
b0 o
b111111111111111111111111111001111 x
b111 }
b111 "
b111 7
b111 E
b111 V
b111 d
b111 r
b111 K
1&
#270000
0&
#275000
1#
1B
b111111111111111111111111111101011 \
b11 `
b11 n
b11111111111111100 |
b11 !
b11 8
b11 D
b11 W
b11 e
b11 s
b11 L
b0 a
b111111111111111111111111111100100 j
b11111111111111001 o
b0 x
b0 }
b0 "
b0 7
b0 E
b0 V
b0 d
b0 r
b0 K
1&
#280000
0&
#285000
b1 a
b111111111111111111111111111101011 j
b11111111111111010 o
b111111111111111111111111111111001 x
b1 }
b1 "
b1 7
b1 E
b1 V
b1 d
b1 r
b1 K
1&
#290000
0&
#295000
b10 a
b111111111111111111111111111110010 j
b11111111111111011 o
b111111111111111111111111111110010 x
b10 }
b10 "
b10 7
b10 E
b10 V
b10 d
b10 r
b10 K
1&
#300000
0&
#305000
b11 a
b111111111111111111111111111111001 j
b11111111111111100 o
b111111111111111111111111111101011 x
b11 }
b11 "
b11 7
b11 E
b11 V
b11 d
b11 r
b11 K
1&
#310000
0&
#315000
b100 a
b0 j
b11111111111111101 o
b111111111111111111111111111100100 x
b100 }
b100 "
b100 7
b100 E
b100 V
b100 d
b100 r
b100 K
1&
#320000
0&
#325000
0#
0B
b101 a
b111 j
b11111111111111110 o
b111111111111111111111111111011101 x
b101 }
b101 "
b101 7
b101 E
b101 V
b101 d
b101 r
b101 K
1&
#330000
0&
#335000
b110 a
b1110 j
b11111111111111111 o
b111111111111111111111111111010110 x
b110 }
b110 "
b110 7
b110 E
b110 V
b110 d
b110 r
b110 K
1&
#340000
0&
#345000
b111 a
b10101 j
b0 o
b111111111111111111111111111001111 x
b111 }
b111 "
b111 7
b111 E
b111 V
b111 d
b111 r
b111 K
1&
#350000
0&
#355000
1#
1B
b111111111111111111111111111100100 \
b100 `
b100 n
b11111111111111101 |
b100 !
b100 8
b100 D
b100 W
b100 e
b100 s
b100 L
b0 a
b111111111111111111111111111101011 j
b11111111111111001 o
b0 x
b0 }
b0 "
b0 7
b0 E
b0 V
b0 d
b0 r
b0 K
1&
#360000
0&
#365000
b1 a
b111111111111111111111111111110010 j
b11111111111111010 o
b111111111111111111111111111111001 x
b1 }
b1 "
b1 7
b1 E
b1 V
b1 d
b1 r
b1 K
1&
#370000
0&
#375000
b10 a
b111111111111111111111111111111001 j
b11111111111111011 o
b111111111111111111111111111110010 x
b10 }
b10 "
b10 7
b10 E
b10 V
b10 d
b10 r
b10 K
1&
#380000
0&
#385000
b11 a
b0 j
b11111111111111100 o
b111111111111111111111111111101011 x
b11 }
b11 "
b11 7
b11 E
b11 V
b11 d
b11 r
b11 K
1&
#390000
0&
#395000
0#
0B
b100 a
b111 j
b11111111111111101 o
b111111111111111111111111111100100 x
b100 }
b100 "
b100 7
b100 E
b100 V
b100 d
b100 r
b100 K
1&
#400000
0&
#405000
b101 a
b1110 j
b11111111111111110 o
b111111111111111111111111111011101 x
b101 }
b101 "
b101 7
b101 E
b101 V
b101 d
b101 r
b101 K
1&
#410000
0&
#415000
b110 a
b10101 j
b11111111111111111 o
b111111111111111111111111111010110 x
b110 }
b110 "
b110 7
b110 E
b110 V
b110 d
b110 r
b110 K
1&
#420000
0&
#425000
b111 a
b11100 j
b0 o
b111111111111111111111111111001111 x
b111 }
b111 "
b111 7
b111 E
b111 V
b111 d
b111 r
b111 K
1&
#430000
0&
#435000
1#
1B
b111111111111111111111111111011101 \
b101 `
b101 n
b11111111111111110 |
b101 !
b101 8
b101 D
b101 W
b101 e
b101 s
b101 L
b0 a
b111111111111111111111111111110010 j
b11111111111111001 o
b0 x
b0 }
b0 "
b0 7
b0 E
b0 V
b0 d
b0 r
b0 K
1&
#440000
0&
#445000
b1 a
b111111111111111111111111111111001 j
b11111111111111010 o
b111111111111111111111111111111001 x
b1 }
b1 "
b1 7
b1 E
b1 V
b1 d
b1 r
b1 K
1&
#450000
0&
#455000
b10 a
b0 j
b11111111111111011 o
b111111111111111111111111111110010 x
b10 }
b10 "
b10 7
b10 E
b10 V
b10 d
b10 r
b10 K
1&
#460000
0&
#465000
0#
0B
b11 a
b111 j
b11111111111111100 o
b111111111111111111111111111101011 x
b11 }
b11 "
b11 7
b11 E
b11 V
b11 d
b11 r
b11 K
1&
#470000
0&
#475000
b100 a
b1110 j
b11111111111111101 o
b111111111111111111111111111100100 x
b100 }
b100 "
b100 7
b100 E
b100 V
b100 d
b100 r
b100 K
1&
#480000
0&
#485000
b101 a
b10101 j
b11111111111111110 o
b111111111111111111111111111011101 x
b101 }
b101 "
b101 7
b101 E
b101 V
b101 d
b101 r
b101 K
1&
#490000
0&
#495000
b110 a
b11100 j
b11111111111111111 o
b111111111111111111111111111010110 x
b110 }
b110 "
b110 7
b110 E
b110 V
b110 d
b110 r
b110 K
1&
#500000
0&
#505000
b111 a
b100011 j
b0 o
b111111111111111111111111111001111 x
b111 }
b111 "
b111 7
b111 E
b111 V
b111 d
b111 r
b111 K
1&
#510000
0&
#515000
1#
1B
b111111111111111111111111111010110 \
b110 `
b110 n
b11111111111111111 |
b110 !
b110 8
b110 D
b110 W
b110 e
b110 s
b110 L
b0 a
b111111111111111111111111111111001 j
b11111111111111001 o
b0 x
b0 }
b0 "
b0 7
b0 E
b0 V
b0 d
b0 r
b0 K
1&
#520000
0&
#525000
b1 a
b0 j
b11111111111111010 o
b111111111111111111111111111111001 x
b1 }
b1 "
b1 7
b1 E
b1 V
b1 d
b1 r
b1 K
1&
#530000
0&
#535000
0#
0B
b10 a
b111 j
b11111111111111011 o
b111111111111111111111111111110010 x
b10 }
b10 "
b10 7
b10 E
b10 V
b10 d
b10 r
b10 K
1&
#540000
0&
#545000
b11 a
b1110 j
b11111111111111100 o
b111111111111111111111111111101011 x
b11 }
b11 "
b11 7
b11 E
b11 V
b11 d
b11 r
b11 K
1&
#550000
0&
#555000
b100 a
b10101 j
b11111111111111101 o
b111111111111111111111111111100100 x
b100 }
b100 "
b100 7
b100 E
b100 V
b100 d
b100 r
b100 K
1&
#560000
0&
#565000
b101 a
b11100 j
b11111111111111110 o
b111111111111111111111111111011101 x
b101 }
b101 "
b101 7
b101 E
b101 V
b101 d
b101 r
b101 K
1&
#570000
0&
#575000
b110 a
b100011 j
b11111111111111111 o
b111111111111111111111111111010110 x
b110 }
b110 "
b110 7
b110 E
b110 V
b110 d
b110 r
b110 K
1&
#580000
0&
#585000
b111 a
b101010 j
b0 o
b111111111111111111111111111001111 x
b111 }
b111 "
b111 7
b111 E
b111 V
b111 d
b111 r
b111 K
1&
#590000
0&
#595000
1#
1B
b111111111111111111111111111001111 \
b111 `
b111 n
b0 |
b111 !
b111 8
b111 D
b111 W
b111 e
b111 s
b111 L
b0 a
b0 j
b11111111111111001 o
b0 x
b0 }
b0 "
b0 7
b0 E
b0 V
b0 d
b0 r
b0 K
1&
#600000
0&
#605000
0#
0B
b1 a
b111 j
b11111111111111010 o
b111111111111111111111111111111001 x
b1 }
b1 "
b1 7
b1 E
b1 V
b1 d
b1 r
b1 K
1&
#610000
0&
#615000
b10 a
b1110 j
b11111111111111011 o
b111111111111111111111111111110010 x
b10 }
b10 "
b10 7
b10 E
b10 V
b10 d
b10 r
b10 K
1&
#620000
0&
#625000
b11 a
b10101 j
b11111111111111100 o
b111111111111111111111111111101011 x
b11 }
b11 "
b11 7
b11 E
b11 V
b11 d
b11 r
b11 K
1&
#630000
0&
#635000
b100 a
b11100 j
b11111111111111101 o
b111111111111111111111111111100100 x
b100 }
b100 "
b100 7
b100 E
b100 V
b100 d
b100 r
b100 K
1&
#640000
0&
#645000
b101 a
b100011 j
b11111111111111110 o
b111111111111111111111111111011101 x
b101 }
b101 "
b101 7
b101 E
b101 V
b101 d
b101 r
b101 K
1&
#650000
0&
#655000
b110 a
b101010 j
b11111111111111111 o
b111111111111111111111111111010110 x
b110 }
b110 "
b110 7
b110 E
b110 V
b110 d
b110 r
b110 K
1&
#660000
0&
#665000
b111 a
b110001 j
b0 o
b111111111111111111111111111001111 x
b111 }
b111 "
b111 7
b111 E
b111 V
b111 d
b111 r
b111 K
1&
#670000
0&
#675000
1B
1%
b11 M
b0 a
b0 j
b11111111111111001 o
b0 x
b0 }
b0 "
b0 7
b0 E
b0 V
b0 d
b0 r
b0 K
1&
#680000
0&
#685000
0%
b0 M
b1000 4
b1000 3
b0 2
1&
